[{"CaseId":16,"CreatedOn":"2020-06-02 14:01","Description":"Demo Step 007 UC Growth and Bound","EditedOn":"2025-03-27 12:31","EndingYear":"2020","FixResultFileName":"False","FixResultInfo":{"WorkTimesFolderPath":null,"GdxElasticDermands":{"GdxSelectedFile":{"FileName":"","FilePath":"","IsSelected":false},"IsApplied":false},"GdxIre":{"GdxSelectedFile":{"FileName":"","FilePath":"","IsSelected":false},"IsApplied":false,"RadioSelection":1},"GdxUseSolution":{"FixYearsUpto":"","GdxSelectedFile":{"FileName":"","FilePath":"","IsSelected":false},"IsApplied":false,"RadioSelection":1},"IsApplyFixResult":false},"GAMSSourceFolder":"GAMS_SrcTIMES.v4.8.3","Name":"DemoS_007c","ParametricGroup":null,"ParametricGroupId":null,"PeriodsDefinition":"pdef-5","PropertiesGroup":"DefaultProperties","PropertiesGroupId":33,"RegionGroup":"AllRegion","RegionGroupId":32,"ScenarioGroup":"DemoS_007c","ScenarioGroupId":37,"Solver":"cplex","SolverOptionFile":"BA121-7","UserName":"86150"},{"CaseId":15,"CreatedOn":"2020-06-02 14:00","Description":"Demo Step 007 Elastic Demand","EditedOn":"2025-03-27 12:31","EndingYear":"2020","FixResultFileName":"False","FixResultInfo":{"WorkTimesFolderPath":null,"GdxElasticDermands":{"GdxSelectedFile":{"FileName":"","FilePath":"","IsSelected":false},"IsApplied":false},"GdxIre":{"GdxSelectedFile":{"FileName":"","FilePath":"","IsSelected":false},"IsApplied":false,"RadioSelection":1},"GdxUseSolution":{"FixYearsUpto":"","GdxSelectedFile":{"FileName":"","FilePath":"","IsSelected":false},"IsApplied":false,"RadioSelection":1},"IsApplyFixResult":false},"GAMSSourceFolder":"GAMS_SrcTIMES.v4.8.3","Name":"DemoS_007b","ParametricGroup":null,"ParametricGroupId":null,"PeriodsDefinition":"pdef-5","PropertiesGroup":"DefaultProperties","PropertiesGroupId":33,"RegionGroup":"AllRegion","RegionGroupId":32,"ScenarioGroup":"DemoS_007b","ScenarioGroupId":36,"Solver":"cplex","SolverOptionFile":"BA121-7","UserName":"86150"},{"CaseId":13,"CreatedOn":"2020-06-02 13:56","Description":"Demo Step 007","EditedOn":"2025-03-27 12:31","EndingYear":"2020","FixResultFileName":"False","FixResultInfo":{"WorkTimesFolderPath":null,"GdxElasticDermands":{"GdxSelectedFile":{"FileName":"","FilePath":"","IsSelected":false},"IsApplied":false},"GdxIre":{"GdxSelectedFile":{"FileName":"","FilePath":"","IsSelected":false},"IsApplied":false,"RadioSelection":1},"GdxUseSolution":{"FixYearsUpto":"","GdxSelectedFile":{"FileName":"","FilePath":"","IsSelected":false},"IsApplied":false,"RadioSelection":1},"IsApplyFixResult":false},"GAMSSourceFolder":"GAMS_SrcTIMES.v4.8.3","Name":"DemoS_007","ParametricGroup":null,"ParametricGroupId":null,"PeriodsDefinition":"pdef-5","PropertiesGroup":"DefaultProperties","PropertiesGroupId":33,"RegionGroup":"AllRegion","RegionGroupId":32,"ScenarioGroup":"DemoS_007","ScenarioGroupId":34,"Solver":"cplex","SolverOptionFile":"BA121-7","UserName":"86150"},{"CaseId":14,"CreatedOn":"2020-06-02 13:58","Description":"Demo Step 007 ELC and TRA CO2 Bounds","EditedOn":"2025-03-27 12:31","EndingYear":"2020","FixResultFileName":"False","FixResultInfo":{"WorkTimesFolderPath":null,"GdxElasticDermands":{"GdxSelectedFile":{"FileName":"","FilePath":"","IsSelected":false},"IsApplied":false},"GdxIre":{"GdxSelectedFile":{"FileName":"","FilePath":"","IsSelected":false},"IsApplied":false,"RadioSelection":1},"GdxUseSolution":{"FixYearsUpto":"","GdxSelectedFile":{"FileName":"","FilePath":"","IsSelected":false},"IsApplied":false,"RadioSelection":1},"IsApplyFixResult":false},"GAMSSourceFolder":"GAMS_SrcTIMES.v4.8.3","Name":"DemoS_007a","ParametricGroup":null,"ParametricGroupId":null,"PeriodsDefinition":"pdef-5","PropertiesGroup":"DefaultProperties","PropertiesGroupId":33,"RegionGroup":"AllRegion","RegionGroupId":32,"ScenarioGroup":"DemoS_007a","ScenarioGroupId":35,"Solver":"cplex","SolverOptionFile":"BA121-7","UserName":"86150"}]